[{"height":64,"id":15,"name":"","properties":{},"rotation":0,"type":"","visible":true,"width":576,"x":0,"y":0},{"height":64,"id":16,"name":"","properties":{},"rotation":0,"type":"","visible":true,"width":64,"x":576,"y":0},{"height":32,"id":17,"name":"","properties":{},"rotation":0,"type":"","visible":true,"width":32,"x":608,"y":64},{"height":96,"id":18,"name":"","properties":{},"rotation":0,"type":"","visible":true,"width":32,"x":608,"y":224},{"height":64,"id":19,"name":"","properties":{},"rotation":0,"type":"","visible":true,"width":512,"x":96,"y":256},{"height":64,"id":20,"name":"","properties":{},"rotation":0,"type":"","visible":true,"width":96,"x":0,"y":256},{"height":32,"id":21,"name":"","properties":{},"rotation":0,"type":"","visible":true,"width":32,"x":0,"y":64},{"height":32,"id":22,"name":"","properties":{},"rotation":0,"type":"","visible":true,"width":32,"x":0,"y":224},{"height":32,"id":23,"name":"","properties":{},"rotation":0,"type":"","visible":true,"width":96,"x":32,"y":128},{"height":32,"id":24,"name":"","properties":{},"rotation":0,"type":"","visible":true,"width":96,"x":32,"y":224},{"height":64,"id":25,"name":"","properties":{},"rotation":0,"type":"","visible":true,"width":64,"x":160,"y":192},{"height":96,"id":26,"name":"","properties":{},"rotation":0,"type":"","visible":true,"width":128,"x":256,"y":160},{"height":32,"id":27,"name":"","properties":{},"rotation":0,"type":"","visible":true,"width":128,"x":256,"y":64},{"height":64,"id":28,"name":"","properties":{},"rotation":0,"type":"","visible":true,"width":64,"x":416,"y":192},{"height":32,"id":29,"name":"","properties":{},"rotation":0,"type":"","visible":true,"width":96,"x":512,"y":224},{"height":32,"id":30,"name":"","properties":{},"rotation":0,"type":"","visible":true,"width":96,"x":512,"y":128}]
