[{"height":316,"id":1,"name":"","properties":{},"rotation":0,"type":"","visible":true,"width":60,"x":2,"y":2},{"height":60,"id":3,"name":"","properties":{},"rotation":0,"type":"","visible":true,"width":575,"x":63,"y":1},{"height":261,"id":4,"name":"","properties":{},"rotation":0,"type":"","visible":true,"width":64,"x":576,"y":58},{"height":63,"id":5,"name":"","properties":{},"rotation":0,"type":"","visible":true,"width":167,"x":415,"y":256},{"height":31,"id":6,"name":"","properties":{},"rotation":0,"type":"","visible":true,"width":68,"x":351,"y":288},{"height":61,"id":7,"name":"","properties":{},"rotation":0,"type":"","visible":true,"width":167,"x":56,"y":258},{"height":31,"id":8,"name":"","properties":{},"rotation":0,"type":"","visible":true,"width":64,"x":222,"y":288},{"height":32,"id":9,"name":"","properties":{},"rotation":0,"type":"","visible":true,"width":95,"x":96,"y":191},{"height":31,"id":10,"name":"","properties":{},"rotation":0,"type":"","visible":true,"width":31,"x":128,"y":128},{"height":32,"id":11,"name":"","properties":{},"rotation":0,"type":"","visible":true,"width":34,"x":479,"y":126},{"height":28,"id":12,"name":"","properties":{},"rotation":0,"type":"","visible":true,"width":95,"x":447,"y":192},{"height":33,"id":13,"name":"","properties":{},"rotation":0,"type":"","visible":true,"width":129,"x":254,"y":127},{"height":29,"id":14,"name":"","properties":{},"rotation":0,"type":"","visible":true,"width":110,"x":266,"y":162},{"height":29,"id":16,"name":"","properties":{},"rotation":0,"type":"","visible":true,"width":107,"x":268,"y":190},{"height":24,"id":17,"name":"","properties":{},"rotation":0,"type":"","visible":true,"width":89,"x":278,"y":218}]
